AGouTI-1.0.3.data/scripts/agouti
agouti_pkg/__init__.py
agouti_pkg/agouti
agouti_pkg/agouti_annotate.py
agouti_pkg/agouti_create_database.py
agouti_pkg/argument_parser.py
agouti_pkg/database.py
agouti_pkg/eprint.py
agouti_pkg/header.py
agouti_pkg/miscallaneous.py
agouti_pkg/output_processing.py
agouti_pkg/processing_product.py
agouti_pkg/read_input.py
agouti_pkg/sample_data.tar.gz
agouti_pkg/sequence_ontology.py
agouti_pkg/six.py
agouti_pkg/anytree/__init__.py
agouti_pkg/anytree/dotexport.py
agouti_pkg/anytree/render.py
agouti_pkg/anytree/resolver.py
agouti_pkg/anytree/search.py
agouti_pkg/anytree/walker.py
agouti_pkg/anytree/exporter/__init__.py
agouti_pkg/anytree/exporter/dictexporter.py
agouti_pkg/anytree/exporter/dotexporter.py
agouti_pkg/anytree/exporter/jsonexporter.py
agouti_pkg/anytree/importer/__init__.py
agouti_pkg/anytree/importer/dictimporter.py
agouti_pkg/anytree/importer/indentedstringimporter.py
agouti_pkg/anytree/importer/jsonimporter.py
agouti_pkg/anytree/iterators/__init__.py
agouti_pkg/anytree/iterators/abstractiter.py
agouti_pkg/anytree/iterators/levelordergroupiter.py
agouti_pkg/anytree/iterators/levelorderiter.py
agouti_pkg/anytree/iterators/postorderiter.py
agouti_pkg/anytree/iterators/preorderiter.py
agouti_pkg/anytree/iterators/zigzaggroupiter.py
agouti_pkg/anytree/node/__init__.py
agouti_pkg/anytree/node/anynode.py
agouti_pkg/anytree/node/exceptions.py
agouti_pkg/anytree/node/node.py
agouti_pkg/anytree/node/nodemixin.py
agouti_pkg/anytree/node/util.py
agouti_pkg/anytree/util/__init__.py
agouti_pkg/anytree/util/commonancestors.py
agouti_pkg/gffutils/__init__.py
agouti_pkg/gffutils/attributes.py
agouti_pkg/gffutils/bins.py
agouti_pkg/gffutils/biopython_integration.py
agouti_pkg/gffutils/constants.py
agouti_pkg/gffutils/convert.py
agouti_pkg/gffutils/create.py
agouti_pkg/gffutils/exceptions.py
agouti_pkg/gffutils/feature.py
agouti_pkg/gffutils/gffwriter.py
agouti_pkg/gffutils/helpers.py
agouti_pkg/gffutils/inspect.py
AGouTI-1.0.3.dist-info/LICENSE
AGouTI-1.0.3.dist-info/METADATA
AGouTI-1.0.3.dist-info/WHEEL
AGouTI-1.0.3.dist-info/top_level.txt
AGouTI-1.0.3.dist-info/RECORD
