Metadata-Version: 2.1
Name: AGouTI
Version: 1.0.3
Summary: Annotation of Genomic and Transcriptomic Intervals using GTF/GFF files.
Home-page: https://github.com/zywicki-lab/agouti
Author: Jan Kosinski
Author-email: jankos@amu.edu.pl
License: GNU General Public License
Classifier: License :: OSI Approved :: GNU General Public License (GPL)
Classifier: Programming Language :: Python :: 3
Classifier: Programming Language :: Python :: 3.7
Requires-Python: >=3.7.0
License-File: LICENSE
Requires-Dist: numpy
Requires-Dist: pandas
